json2swagger/__init__.py
json2swagger-0.1.0.dist-info/DESCRIPTION.rst
json2swagger-0.1.0.dist-info/entry_points.txt
json2swagger-0.1.0.dist-info/METADATA
json2swagger-0.1.0.dist-info/metadata.json
json2swagger-0.1.0.dist-info/RECORD
json2swagger-0.1.0.dist-info/top_level.txt
json2swagger-0.1.0.dist-info/WHEEL
