Metadata-Version: 2.0
Name: json2swagger
Version: 0.1.0
Summary: generate swagger spec from json (or yaml) file
Home-page: UNKNOWN
Author: UNKNOWN
Author-email: UNKNOWN
License: UNKNOWN
Platform: UNKNOWN
Classifier: Programming Language :: Python
Classifier: Programming Language :: Python :: Implementation :: CPython
Requires-Dist: dictknife[load]
Requires-Dist: prestring
Provides-Extra: docs
Provides-Extra: testing
